Metadata-Version: 2.4
Name: csvdir
Version: 0.8.0
Summary: Read all csv files in a directory with one iterator.
License: MIT License
Keywords: csv,dict,dir,directory,reader
Requires-Python: >=3.8
